[
    {
        "type": "pause",
        "ons": 0,
        "dur": 5
    },
    {
        "type": "study",
        "dur": 25,
        "ons": 5,
        "problem": 27,
        "problem_idx": 0,
        "order": [
            "B",
            "D",
            "C",
            "A"
        ]
    },
    {
        "type": "choose",
        "dur": 5,
        "ons": 30,
        "problem": 27,
        "problem_idx": 0,
        "ex_idx": 0,
        "order": [
            "B",
            "D",
            "C",
            "A"
        ]
    },
    {
        "type": "pause",
        "dur": 1.25,
        "ons": 35
    },
    {
        "type": "pre",
        "dur": 1,
        "ons": 36.25,
        "problem": 27,
        "problem_idx": 0,
        "ex_idx": 0,
        "order": [
            "B",
            "D",
            "C",
            "A"
        ]
    },
    {
        "type": "show",
        "dur": 2,
        "ons": 37.25,
        "problem": 27,
        "problem_idx": 0,
        "ex_idx": 0,
        "order": [
            "B",
            "D",
            "C",
            "A"
        ]
    },
    {
        "type": "pause",
        "dur": 2.4000000000000004,
        "ons": 39.25
    },
    {
        "type": "rate",
        "dur": 2,
        "ons": 41.65,
        "problem": 27,
        "problem_idx": 0,
        "ex_idx": 0,
        "order": [
            "B",
            "D",
            "C",
            "A"
        ]
    },
    {
        "type": "pause",
        "ons": 43.65,
        "dur": 1.3
    },
    {
        "type": "choose",
        "dur": 5,
        "ons": 44.949999999999996,
        "problem": 27,
        "problem_idx": 0,
        "ex_idx": 1,
        "order": [
            "B",
            "D",
            "C",
            "A"
        ]
    },
    {
        "type": "pause",
        "dur": 2.2,
        "ons": 49.949999999999996
    },
    {
        "type": "pre",
        "dur": 1,
        "ons": 52.15,
        "problem": 27,
        "problem_idx": 0,
        "ex_idx": 1,
        "order": [
            "B",
            "D",
            "C",
            "A"
        ]
    },
    {
        "type": "show",
        "dur": 2,
        "ons": 53.15,
        "problem": 27,
        "problem_idx": 0,
        "ex_idx": 1,
        "order": [
            "B",
            "D",
            "C",
            "A"
        ]
    },
    {
        "type": "pause",
        "dur": 1.8,
        "ons": 55.15
    },
    {
        "type": "rate",
        "dur": 2,
        "ons": 56.949999999999996,
        "problem": 27,
        "problem_idx": 0,
        "ex_idx": 1,
        "order": [
            "B",
            "D",
            "C",
            "A"
        ]
    },
    {
        "type": "pause",
        "ons": 58.949999999999996,
        "dur": 0.75
    },
    {
        "type": "choose",
        "dur": 5,
        "ons": 59.699999999999996,
        "problem": 27,
        "problem_idx": 0,
        "ex_idx": 2,
        "order": [
            "B",
            "D",
            "C",
            "A"
        ]
    },
    {
        "type": "pause",
        "dur": 0.9,
        "ons": 64.69999999999999
    },
    {
        "type": "pre",
        "dur": 1,
        "ons": 65.6,
        "problem": 27,
        "problem_idx": 0,
        "ex_idx": 2,
        "order": [
            "B",
            "D",
            "C",
            "A"
        ]
    },
    {
        "type": "show",
        "dur": 2,
        "ons": 66.6,
        "problem": 27,
        "problem_idx": 0,
        "ex_idx": 2,
        "order": [
            "B",
            "D",
            "C",
            "A"
        ]
    },
    {
        "type": "pause",
        "dur": 2.0,
        "ons": 68.6
    },
    {
        "type": "rate",
        "dur": 2,
        "ons": 70.6,
        "problem": 27,
        "problem_idx": 0,
        "ex_idx": 2,
        "order": [
            "B",
            "D",
            "C",
            "A"
        ]
    },
    {
        "type": "pause",
        "ons": 72.6,
        "dur": 0.85
    },
    {
        "type": "pause",
        "ons": 73.44999999999999,
        "dur": 7.0
    },
    {
        "type": "study",
        "dur": 25,
        "ons": 80.44999999999999,
        "problem": 34,
        "problem_idx": 1,
        "order": [
            "A",
            "C",
            "B",
            "D"
        ]
    },
    {
        "type": "choose",
        "dur": 5,
        "ons": 105.44999999999999,
        "problem": 34,
        "problem_idx": 1,
        "ex_idx": 0,
        "order": [
            "A",
            "C",
            "B",
            "D"
        ]
    },
    {
        "type": "pause",
        "dur": 0.8,
        "ons": 110.44999999999999
    },
    {
        "type": "pre",
        "dur": 1,
        "ons": 111.24999999999999,
        "problem": 34,
        "problem_idx": 1,
        "ex_idx": 0,
        "order": [
            "A",
            "C",
            "B",
            "D"
        ]
    },
    {
        "type": "show",
        "dur": 2,
        "ons": 112.24999999999999,
        "problem": 34,
        "problem_idx": 1,
        "ex_idx": 0,
        "order": [
            "A",
            "C",
            "B",
            "D"
        ]
    },
    {
        "type": "pause",
        "dur": 2.1,
        "ons": 114.24999999999999
    },
    {
        "type": "rate",
        "dur": 2,
        "ons": 116.34999999999998,
        "problem": 34,
        "problem_idx": 1,
        "ex_idx": 0,
        "order": [
            "A",
            "C",
            "B",
            "D"
        ]
    },
    {
        "type": "pause",
        "ons": 118.34999999999998,
        "dur": 1.6
    },
    {
        "type": "choose",
        "dur": 5,
        "ons": 119.94999999999997,
        "problem": 34,
        "problem_idx": 1,
        "ex_idx": 1,
        "order": [
            "A",
            "C",
            "B",
            "D"
        ]
    },
    {
        "type": "pause",
        "dur": 2.05,
        "ons": 124.94999999999997
    },
    {
        "type": "pre",
        "dur": 1,
        "ons": 126.99999999999997,
        "problem": 34,
        "problem_idx": 1,
        "ex_idx": 1,
        "order": [
            "A",
            "C",
            "B",
            "D"
        ]
    },
    {
        "type": "show",
        "dur": 2,
        "ons": 127.99999999999997,
        "problem": 34,
        "problem_idx": 1,
        "ex_idx": 1,
        "order": [
            "A",
            "C",
            "B",
            "D"
        ]
    },
    {
        "type": "pause",
        "dur": 1.4,
        "ons": 129.99999999999997
    },
    {
        "type": "rate",
        "dur": 2,
        "ons": 131.39999999999998,
        "problem": 34,
        "problem_idx": 1,
        "ex_idx": 1,
        "order": [
            "A",
            "C",
            "B",
            "D"
        ]
    },
    {
        "type": "pause",
        "ons": 133.39999999999998,
        "dur": 1.15
    },
    {
        "type": "choose",
        "dur": 5,
        "ons": 134.54999999999998,
        "problem": 34,
        "problem_idx": 1,
        "ex_idx": 2,
        "order": [
            "A",
            "C",
            "B",
            "D"
        ]
    },
    {
        "type": "pause",
        "dur": 1.65,
        "ons": 139.54999999999998
    },
    {
        "type": "pre",
        "dur": 1,
        "ons": 141.2,
        "problem": 34,
        "problem_idx": 1,
        "ex_idx": 2,
        "order": [
            "A",
            "C",
            "B",
            "D"
        ]
    },
    {
        "type": "show",
        "dur": 2,
        "ons": 142.2,
        "problem": 34,
        "problem_idx": 1,
        "ex_idx": 2,
        "order": [
            "A",
            "C",
            "B",
            "D"
        ]
    },
    {
        "type": "pause",
        "dur": 0.95,
        "ons": 144.2
    },
    {
        "type": "rate",
        "dur": 2,
        "ons": 145.14999999999998,
        "problem": 34,
        "problem_idx": 1,
        "ex_idx": 2,
        "order": [
            "A",
            "C",
            "B",
            "D"
        ]
    },
    {
        "type": "pause",
        "ons": 147.14999999999998,
        "dur": 1.05
    },
    {
        "type": "pause",
        "ons": 148.2,
        "dur": 3.0
    },
    {
        "type": "study",
        "dur": 25,
        "ons": 151.2,
        "problem": 28,
        "problem_idx": 2,
        "order": [
            "A",
            "B",
            "C",
            "D"
        ]
    },
    {
        "type": "choose",
        "dur": 5,
        "ons": 176.2,
        "problem": 28,
        "problem_idx": 2,
        "ex_idx": 0,
        "order": [
            "A",
            "B",
            "C",
            "D"
        ]
    },
    {
        "type": "pause",
        "dur": 1.9500000000000002,
        "ons": 181.2
    },
    {
        "type": "pre",
        "dur": 1,
        "ons": 183.14999999999998,
        "problem": 28,
        "problem_idx": 2,
        "ex_idx": 0,
        "order": [
            "A",
            "B",
            "C",
            "D"
        ]
    },
    {
        "type": "show",
        "dur": 2,
        "ons": 184.14999999999998,
        "problem": 28,
        "problem_idx": 2,
        "ex_idx": 0,
        "order": [
            "A",
            "B",
            "C",
            "D"
        ]
    },
    {
        "type": "pause",
        "dur": 2.25,
        "ons": 186.14999999999998
    },
    {
        "type": "rate",
        "dur": 2,
        "ons": 188.39999999999998,
        "problem": 28,
        "problem_idx": 2,
        "ex_idx": 0,
        "order": [
            "A",
            "B",
            "C",
            "D"
        ]
    },
    {
        "type": "pause",
        "ons": 190.39999999999998,
        "dur": 2.5
    },
    {
        "type": "choose",
        "dur": 5,
        "ons": 192.89999999999998,
        "problem": 28,
        "problem_idx": 2,
        "ex_idx": 1,
        "order": [
            "A",
            "B",
            "C",
            "D"
        ]
    },
    {
        "type": "pause",
        "dur": 1.7000000000000002,
        "ons": 197.89999999999998
    },
    {
        "type": "pre",
        "dur": 1,
        "ons": 199.59999999999997,
        "problem": 28,
        "problem_idx": 2,
        "ex_idx": 1,
        "order": [
            "A",
            "B",
            "C",
            "D"
        ]
    },
    {
        "type": "show",
        "dur": 2,
        "ons": 200.59999999999997,
        "problem": 28,
        "problem_idx": 2,
        "ex_idx": 1,
        "order": [
            "A",
            "B",
            "C",
            "D"
        ]
    },
    {
        "type": "pause",
        "dur": 1.1,
        "ons": 202.59999999999997
    },
    {
        "type": "rate",
        "dur": 2,
        "ons": 203.69999999999996,
        "problem": 28,
        "problem_idx": 2,
        "ex_idx": 1,
        "order": [
            "A",
            "B",
            "C",
            "D"
        ]
    },
    {
        "type": "pause",
        "ons": 205.69999999999996,
        "dur": 1.5
    },
    {
        "type": "choose",
        "dur": 5,
        "ons": 207.19999999999996,
        "problem": 28,
        "problem_idx": 2,
        "ex_idx": 2,
        "order": [
            "A",
            "B",
            "C",
            "D"
        ]
    },
    {
        "type": "pause",
        "dur": 2.35,
        "ons": 212.19999999999996
    },
    {
        "type": "pre",
        "dur": 1,
        "ons": 214.54999999999995,
        "problem": 28,
        "problem_idx": 2,
        "ex_idx": 2,
        "order": [
            "A",
            "B",
            "C",
            "D"
        ]
    },
    {
        "type": "show",
        "dur": 2,
        "ons": 215.54999999999995,
        "problem": 28,
        "problem_idx": 2,
        "ex_idx": 2,
        "order": [
            "A",
            "B",
            "C",
            "D"
        ]
    },
    {
        "type": "pause",
        "dur": 2.45,
        "ons": 217.54999999999995
    },
    {
        "type": "rate",
        "dur": 2,
        "ons": 219.99999999999994,
        "problem": 28,
        "problem_idx": 2,
        "ex_idx": 2,
        "order": [
            "A",
            "B",
            "C",
            "D"
        ]
    },
    {
        "type": "pause",
        "ons": 221.99999999999994,
        "dur": 1.55
    },
    {
        "type": "pause",
        "ons": 223.54999999999995,
        "dur": 5.0
    },
    {
        "type": "study",
        "dur": 25,
        "ons": 228.54999999999995,
        "problem": 39,
        "problem_idx": 3,
        "order": [
            "C",
            "D",
            "B",
            "A"
        ]
    },
    {
        "type": "choose",
        "dur": 5,
        "ons": 253.54999999999995,
        "problem": 39,
        "problem_idx": 3,
        "ex_idx": 0,
        "order": [
            "C",
            "D",
            "B",
            "A"
        ]
    },
    {
        "type": "pause",
        "dur": 2.3,
        "ons": 258.54999999999995
    },
    {
        "type": "pre",
        "dur": 1,
        "ons": 260.84999999999997,
        "problem": 39,
        "problem_idx": 3,
        "ex_idx": 0,
        "order": [
            "C",
            "D",
            "B",
            "A"
        ]
    },
    {
        "type": "show",
        "dur": 2,
        "ons": 261.84999999999997,
        "problem": 39,
        "problem_idx": 3,
        "ex_idx": 0,
        "order": [
            "C",
            "D",
            "B",
            "A"
        ]
    },
    {
        "type": "pause",
        "dur": 1.0,
        "ons": 263.84999999999997
    },
    {
        "type": "rate",
        "dur": 2,
        "ons": 264.84999999999997,
        "problem": 39,
        "problem_idx": 3,
        "ex_idx": 0,
        "order": [
            "C",
            "D",
            "B",
            "A"
        ]
    },
    {
        "type": "pause",
        "ons": 266.84999999999997,
        "dur": 2.1500000000000004
    },
    {
        "type": "choose",
        "dur": 5,
        "ons": 268.99999999999994,
        "problem": 39,
        "problem_idx": 3,
        "ex_idx": 1,
        "order": [
            "C",
            "D",
            "B",
            "A"
        ]
    },
    {
        "type": "pause",
        "dur": 1.2,
        "ons": 273.99999999999994
    },
    {
        "type": "pre",
        "dur": 1,
        "ons": 275.19999999999993,
        "problem": 39,
        "problem_idx": 3,
        "ex_idx": 1,
        "order": [
            "C",
            "D",
            "B",
            "A"
        ]
    },
    {
        "type": "show",
        "dur": 2,
        "ons": 276.19999999999993,
        "problem": 39,
        "problem_idx": 3,
        "ex_idx": 1,
        "order": [
            "C",
            "D",
            "B",
            "A"
        ]
    },
    {
        "type": "pause",
        "dur": 1.4500000000000002,
        "ons": 278.19999999999993
    },
    {
        "type": "rate",
        "dur": 2,
        "ons": 279.6499999999999,
        "problem": 39,
        "problem_idx": 3,
        "ex_idx": 1,
        "order": [
            "C",
            "D",
            "B",
            "A"
        ]
    },
    {
        "type": "pause",
        "ons": 281.6499999999999,
        "dur": 1.35
    },
    {
        "type": "choose",
        "dur": 5,
        "ons": 282.99999999999994,
        "problem": 39,
        "problem_idx": 3,
        "ex_idx": 2,
        "order": [
            "C",
            "D",
            "B",
            "A"
        ]
    },
    {
        "type": "pause",
        "dur": 1.85,
        "ons": 287.99999999999994
    },
    {
        "type": "pre",
        "dur": 1,
        "ons": 289.84999999999997,
        "problem": 39,
        "problem_idx": 3,
        "ex_idx": 2,
        "order": [
            "C",
            "D",
            "B",
            "A"
        ]
    },
    {
        "type": "show",
        "dur": 2,
        "ons": 290.84999999999997,
        "problem": 39,
        "problem_idx": 3,
        "ex_idx": 2,
        "order": [
            "C",
            "D",
            "B",
            "A"
        ]
    },
    {
        "type": "pause",
        "dur": 1.9000000000000001,
        "ons": 292.84999999999997
    },
    {
        "type": "rate",
        "dur": 2,
        "ons": 294.74999999999994,
        "problem": 39,
        "problem_idx": 3,
        "ex_idx": 2,
        "order": [
            "C",
            "D",
            "B",
            "A"
        ]
    },
    {
        "type": "pause",
        "ons": 296.74999999999994,
        "dur": 1.75
    },
    {
        "type": "pause",
        "dur": 5,
        "ons": 298.49999999999994
    }
]